{"stat.flyOneCm":76600,"stat.walkOneCm":17190,"stat.jump":83,"stat.pickup.minecraft.egg":1,"stat.playOneMinute":30723,"stat.pickup.ic2.tfbp":1,"stat.useItem.nebulus.nebulitemeteor":9,"stat.killEntity.Chicken":1,"stat.leaveGame":1,"stat.sneakTime":869,"stat.damageDealt":146,"stat.pickup.ic2.scaffold":1,"stat.crouchOneCm":537,"stat.timeSinceDeath":30723,"stat.useItem.ic2.debug_item":3,"stat.mobKills":2,"stat.sprintOneCm":1109,"stat.pickup.nebulus.nebulitemeteor":5,"stat.useItem.minecraft.stone_slab2":31,"stat.useItem.minecraft.spawn_egg":5,"stat.killEntity.watergolem":1}